circulartape/__init__.py
circulartape-0.0.3.dist-info/METADATA
circulartape-0.0.3.dist-info/RECORD
circulartape-0.0.3.dist-info/WHEEL
circulartape-0.0.3.dist-info/top_level.txt
