Metadata-Version: 2.1
Name: circulartape
Version: 0.0.3
Summary: A circular linked list implementation
Home-page: UNKNOWN
Author: Tris Emmy Wilson
Author-email: anemptystring@gmail.com
License: UNKNOWN
Platform: UNKNOWN
Classifier: Programming Language :: Python :: 3
Classifier: License :: OSI Approved :: MIT License
Classifier: Operating System :: OS Independent
